source/__init__.py
source/__main__.py
source/cli.py
source/github_repository.py
repo_reasoner-0.0.33.dist-info/LICENSE.txt
repo_reasoner-0.0.33.dist-info/METADATA
repo_reasoner-0.0.33.dist-info/WHEEL
repo_reasoner-0.0.33.dist-info/entry_points.txt
repo_reasoner-0.0.33.dist-info/top_level.txt
repo_reasoner-0.0.33.dist-info/RECORD
