Metadata-Version: 2.2
Name: repo-reasoner
Version: 0.0.33
Summary: Repository reasoner that uses LLM, instead of a real project or framework or library
Home-page: https://github.com/dzhovi/repositories-reasoner
Author: Vakhidov Dzhovidon
Author-email: asunabestwaifu1@gmail.com
Classifier: Intended Audience :: Developers
Classifier: License :: OSI Approved :: MIT License
Classifier: Programming Language :: Python :: 3.9
Classifier: Programming Language :: Python :: 3.10
Classifier: Programming Language :: Python :: 3.11
License-File: LICENSE.txt
Requires-Dist: pytest==8.2.2
Requires-Dist: pytest-cov==5.0.0
Requires-Dist: coveralls==3.3.1
Requires-Dist: langchain-gigachat==0.3.2
Requires-Dist: pytest-mock==3.10.0
Requires-Dist: typer==0.15.1
Dynamic: author
Dynamic: author-email
Dynamic: classifier
Dynamic: description
Dynamic: description-content-type
Dynamic: home-page
Dynamic: requires-dist
Dynamic: summary
